chained_recurrence/__init__.py
chained_recurrence/__main__.py
chained_recurrence/on-modify-chained.py
chained_recurrence-0.0.13.dist-info/LICENCE
chained_recurrence-0.0.13.dist-info/METADATA
chained_recurrence-0.0.13.dist-info/WHEEL
chained_recurrence-0.0.13.dist-info/entry_points.txt
chained_recurrence-0.0.13.dist-info/top_level.txt
chained_recurrence-0.0.13.dist-info/RECORD
