Metadata-Version: 2.1
Name: chained-recurrence
Version: 0.0.13
Summary: Painless chained recurrence for Taskwarrior.
Author-email: Matt Deacalion Stevens <matt@dirtymonkey.co.uk>
License: ISC License
Project-URL: Documentation, https://codeberg.org/Dokana/Taskwarrior-Chained/#user-content-taskwarrior-chained-recurrence-hook
Project-URL: Issues, https://codeberg.org/Dokana/Taskwarrior-Chained/issues
Project-URL: Source, https://codeberg.org/Dokana/Taskwarrior-Chained
Keywords: taskwarrior,reccuring,repeating,tasks
Classifier: Development Status :: 4 - Beta
Classifier: Environment :: Console
Classifier: Environment :: Plugins
Classifier: License :: OSI Approved :: ISC License (ISCL)
Classifier: Operating System :: POSIX
Classifier: Operating System :: POSIX :: BSD
Classifier: Operating System :: POSIX :: Linux
Classifier: Programming Language :: Python :: 3.8
Classifier: Programming Language :: Python :: 3.9
Classifier: Programming Language :: Python :: 3.10
Classifier: Programming Language :: Python :: 3.11
Classifier: Programming Language :: Python :: 3.12
Classifier: Programming Language :: Python :: Implementation :: CPython
Classifier: Topic :: Office/Business
Classifier: Topic :: Office/Business :: News/Diary
Classifier: Topic :: Office/Business :: Scheduling
Classifier: Topic :: Utilities
Requires-Python: >=3.8
License-File: LICENCE
Requires-Dist: click >=8.1.3
Requires-Dist: psutil >=5.9.5
Requires-Dist: tasklib >=2.5.1
Provides-Extra: dev
Requires-Dist: black ; extra == 'dev'
Requires-Dist: isort ; extra == 'dev'
